ALU_Decoder/ALU_Decoder.vhdl
library ieee;
use ieee.std_logic_1164.all;
use ieee.numeric_std.all;

entity ALU_Decoder is
    port(
        op5 : in std_logic;
        funct3 : in std_logic_vector(2 downto 0);
        funct7_5 : in std_logic;
        ALUOp : in std_logic_vector(1 downto 0);
        ALUControl : out std_logic_vector(2 downto 0)
    );
end ALU_Decoder;

architecture rtl of ALU_Decoder is
    begin
        process(op5, funct3, funct7_5, ALUOp) begin
            case ALUOp is
                when "00" => ALUControl <= "000"; --add
                when "01" => if((funct3(0) and funct7_5) = '1') then
                                ALUControl <= "101"; --sub
                              else
                                ALUControl <= "001";
                              end if;
                when others => case funct3 is
                            when "000" => if ((op5 and funct7_5) = '1') then
                                                ALUControl <= "001"; --sub
                                          else
                                                ALUControl <= "000"; --add
                                          end if;
                            when "010" => ALUControl <= "101"; --slt
                            when "110" => ALUControl <= "011"; --or
                            when "111" => ALUControl <= "010"; --and
                            when "101" => ALUControl <= "100"; --srl
                            when others => ALUControl <= "---"; --undefined
                            end case;
            end case;
        end process;
    end rtl;

ALU_Decoder/anyname.vcd
$date
  Thu Dec 16 23:55:16 2021
$end
$version
  GHDL v0
$end
$timescale
  1 fs
$end
$scope module standard $end
$upscope $end
$scope module std_logic_1164 $end
$upscope $end
$scope module numeric_std $end
$upscope $end
$scope module alu_decoder $end
$var reg 1 ! op5 $end
$var reg 3 " funct3[2:0] $end
$var reg 1 # funct7_5 $end
$var reg 2 $ aluop[1:0] $end
$var reg 3 % alucontrol[2:0] $end
$upscope $end
$enddefinitions $end
#0
1!
b100 "
0#
b11 $
b110 %
#5000000
0!
b011 "
1#
b--- %
#10000000
1!
b100 "
b01 $
b001 %
#15000000
b111 "
0#
b00 $
b000 %
#20000000
b000 "
1#
#25000000
b010 "
b11 $
b101 %
#30000000
0!
b001 "
0#
b00 $
b000 %
#35000000
1!
b10 $
b111 %
#40000000
0!
b11 $
#45000000
b000 "
b10 $
b000 %
#50000000
b010 "
1#
b11 $
b101 %
#55000000
b000 "
b01 $
b001 %
#60000000
1!
b100 "
0#
b10 $
b110 %
#65000000
0!
b110 "
b011 %
#70000000
1!
1#
b01 $
b001 %
