adder/adder.vhdl
library ieee;
use ieee.std_logic_1164.all;
use ieee.numeric_std.all;

entity adder is
    generic(numberbits_b : integer := 32);
    port(
        --inputs
        a_in    : in std_logic_vector(31 downto 0);
        b_in    : in std_logic_vector(numberbits_b-1 downto 0);
        --output
        c_out   : out std_logic_vector(31 downto 0)
    );
end adder;

architecture rtl of adder is
    begin
    
        c_out <= std_logic_vector(unsigned(a_in) + unsigned(b_in));
    
    end rtl;

adder/anyname.vcd
$date
  Wed Dec 22 15:14:15 2021
$end
$version
  GHDL v0
$end
$timescale
  1 fs
$end
$scope module standard $end
$upscope $end
$scope module std_logic_1164 $end
$upscope $end
$scope module numeric_std $end
$upscope $end
$scope module adder $end
$var reg 32 ! a_in[31:0] $end
$var reg 32 " b_in[31:0] $end
$var reg 32 # c_out[31:0] $end
$upscope $end
$enddefinitions $end
#0
b00000000000000000000000011111111 !
b00000000000000000000000000001100 "
b00000000000000000000000100001011 #
#5000000
#5000001
b00000000000000000011011001001111 !
b00000000000000000101110000110100 "
b00000000000000001001001010000011 #
#10000001
b00000000000000000100011101000100 !
b00000000000000000101011001000100 "
b00000000000000001001110110001000 #
#15000001
b00000000000000000000011100010111 !
b00000000000000000100101110000001 "
b00000000000000000101001010011000 #
#20000001
b00000000000000001001101011010000 !
b00000000000000000111111110000010 "
b00000000000000010001101001010010 #
#25000001
b00000000000000000001101000111100 !
b00000000000000001000000001110001 "
b00000000000000001001101010101101 #
#30000001
b00000000000000000011100001110000 !
b00000000000000000000001100100110 "
b00000000000000000011101110010110 #
#35000001
b00000000000000001001111100011101 !
b00000000000000001000010100001110 "
b00000000000000010010010000101011 #
#40000001
b00000000000000000000100111010110 !
b00000000000000000100111001100001 "
b00000000000000000101100000110111 #
#45000001
b00000000000000000001011111011000 !
b00000000000000001000010001101010 "
b00000000000000001001110001000010 #
#50000001
b00000000000000001001110100111001 !
b00000000000000000001101001011110 "
b00000000000000001011011110010111 #
