adder/adder.vhdl
library ieee;
use ieee.std_logic_1164.all;
use ieee.numeric_std.all;

entity adder is
    generic(numberbits_b : integer := 32);
    port(
        --inputs
        a_in    : in std_logic_vector(31 downto 0);
        b_in    : in std_logic_vector(numberbits_b-1 downto 0);
        --output
        c_out   : out std_logic_vector(31 downto 0)
    );
end adder;

architecture rtl of adder is
    begin
    
        c_out <= std_logic_vector(unsigned(a_in) + unsigned(b_in));
    
    end rtl;

adder/anyname.vcd
$date
  Thu Dec 16 21:52:38 2021
$end
$version
  GHDL v0
$end
$timescale
  1 fs
$end
$scope module standard $end
$upscope $end
$scope module std_logic_1164 $end
$upscope $end
$scope module numeric_std $end
$upscope $end
$scope module adder $end
$var reg 32 ! a_in[31:0] $end
$var reg 32 " b_in[31:0] $end
$var reg 32 # c_out[31:0] $end
$upscope $end
$enddefinitions $end
#0
b00000000000000000000000011111111 !
b00000000000000000000000000001100 "
b00000000000000000000000100001011 #
#5000000
#5000001
b00000000000000000111111011111101 !
b00000000000000000001010101110001 "
b00000000000000001001010001101110 #
#10000001
b00000000000000000001101111001110 !
b00000000000000000010001010111101 "
b00000000000000000011111010001011 #
#15000001
b00000000000000000101100001001001 !
b00000000000000000100101101001111 "
b00000000000000001010001110011000 #
#20000001
b00000000000000000001011111010100 !
b00000000000000000111100100000110 "
b00000000000000001001000011011010 #
#25000001
b00000000000000001001101110011000 !
b00000000000000001011001000001111 "
b00000000000000010100110110100111 #
#30000001
b00000000000000000110000111110011 !
b00000000000000001000000011111000 "
b00000000000000001110001011101011 #
#35000001
b00000000000000000101100111101010 !
b00000000000000001001100001011001 "
b00000000000000001111001001000011 #
#40000001
b00000000000000001010011000001001 !
b00000000000000001011001001101010 "
b00000000000000010101100001110011 #
#45000001
b00000000000000001011101110011011 !
b00000000000000001011101010011001 "
b00000000000000010111011000110100 #
#50000001
b00000000000000000001101100010100 !
b00000000000000000111010110100111 "
b00000000000000001001000010111011 #
