data_memory/data_memr.vhdl
library ieee;
use ieee.std_logic_1164.all;
use ieee.numeric_std.all;

entity data_memr is
    port(
        --inputs
        addr_port   : in std_logic_vector(31 downto 0);
        write_data  : in std_logic_vector(31 downto 0);
        clk         : in std_logic;
        write_en    : in std_logic;
        --output
        read_data   : out std_logic_vector(31 downto 0)
    );
end data_memr;

architecture rtl of data_memr is

    type ram_type is array (63 downto 0) of std_logic_vector(31 downto 0);

    signal mem : ram_type := (others => (others => '0'));

    begin

        process(addr_port)begin
            read_data <= mem(to_integer(unsigned(addr_port(7 downto 2))));
        end process;

        process(clk) begin
                if rising_edge(clk) then
                    if(write_en = '1')then
                        mem(to_integer(unsigned(addr_port(7 downto 2)))) <= write_data;
                    end if;
                end if;
        end process;

    end rtl;

data_memory/anyname.vcd
$date
  Fri Dec 17 18:22:45 2021
$end
$version
  GHDL v0
$end
$timescale
  1 fs
$end
$scope module standard $end
$upscope $end
$scope module std_logic_1164 $end
$upscope $end
$scope module numeric_std $end
$upscope $end
$scope module data_memr $end
$var reg 32 ! addr_port[31:0] $end
$var reg 32 " write_data[31:0] $end
$var reg 1 # clk $end
$var reg 1 $ write_en $end
$var reg 32 % read_data[31:0] $end
$comment mem is not handled $end
$upscope $end
$enddefinitions $end
#0
b00000000000000000000000010000110 !
b00000000000000000000000000110110 "
1#
0$
b00000000000000000000000000000000 %
#5000000000
0#
#10000000000
b00000000000000000000000001011010 !
b00000000000000000000000001111111 "
1#
1$
#15000000000
0#
#20000000000
b00000000000000000000000000111100 !
b00000000000000000000000010011111 "
1#
#25000000000
0#
#30000000000
b00000000000000000000000001100101 !
b00000000000000000000000000000011 "
1#
0$
#35000000000
0#
#40000000000
b00000000000000000000000001100001 !
b00000000000000000000000010001100 "
1#
#45000000000
0#
#50000000000
b00000000000000000000000011100110 !
b00000000000000000000000010010101 "
1#
#55000000000
0#
#60000000000
b00000000000000000000000011001011 !
b00000000000000000000000001010111 "
1#
1$
#65000000000
0#
#70000000000
b00000000000000000000000010110011 !
b00000000000000000000000010001101 "
1#
#75000000000
0#
#80000000000
b00000000000000000000000011101110 !
b00000000000000000000000000101001 "
1#
#85000000000
0#
#90000000000
b00000000000000000000000001001100 !
b00000000000000000000000011110011 "
1#
#95000000000
0#
#100000000000
b00000000000000000000000000011111 !
b00000000000000000000000001011000 "
1#
0$
#105000000000
0#
#110000000000
b00000000000000000000000011101100 !
b00000000000000000000000011010100 "
1#
1$
b00000000000000000000000000101001 %
#115000000000
0#
#120000000000
b00000000000000000000000011010011 !
b00000000000000000000000000100101 "
1#
0$
b00000000000000000000000000000000 %
#125000000000
0#
#130000000000
b00000000000000000000000011010111 !
b00000000000000000000000001100001 "
1#
1$
#135000000000
0#
#140000000000
b00000000000000000000000000010101 !
b00000000000000000000000010000001 "
1#
0$
#145000000000
0#
#150000000000
b00000000000000000000000001010101 !
b00000000000000000000000010110010 "
1#
#155000000000
0#
#160000000000
b00000000000000000000000010001111 !
b00000000000000000000000001000010 "
1#
1$
#165000000000
0#
#170000000000
b00000000000000000000000010001011 !
b00000000000000000000000010100110 "
1#
0$
#175000000000
0#
#180000000000
b00000000000000000000000010100010 !
b00000000000000000000000011001011 "
1#
#185000000000
0#
#190000000000
b00000000000000000000000001101111 !
b00000000000000000000000001011111 "
1#
1$
#195000000000
0#
#200000000000
b00000000000000000000000001111011 !
b00000000000000000000000011001101 "
1#
#205000000000
0#
#210000000000
b00000000000000000000000000000011 !
b00000000000000000000000011011000 "
1#
#215000000000
0#
#220000000000
b00000000000000000000000011000000 !
b00000000000000000000000000100110 "
1#
0$
#225000000000
0#
#230000000000
b00000000000000000000000010011100 !
b00000000000000000000000001100010 "
1#
#235000000000
0#
#240000000000
b00000000000000000000000010111101 !
b00000000000000000000000000111101 "
1#
#245000000000
0#
#250000000000
b00000000000000000000000000011010 !
b00000000000000000000000011100010 "
1#
#255000000000
0#
#260000000000
b00000000000000000000000010001011 !
b00000000000000000000000010011110 "
1#
1$
#265000000000
0#
#270000000000
b00000000000000000000000001111011 !
b00000000000000000000000001111111 "
1#
b00000000000000000000000011001101 %
#275000000000
0#
#280000000000
b00000000000000000000000011100001 !
b00000000000000000000000011001101 "
1#
b00000000000000000000000000000000 %
#285000000000
0#
#290000000000
b00000000000000000000000001110110 !
b00000000000000000000000000011100 "
1#
#295000000000
0#
#300000000000
b00000000000000000000000001111111 !
b00000000000000000000000000111010 "
1#
#305000000000
0#
#310000000000
b00000000000000000000000001100101 !
b00000000000000000000000001100101 "
1#
#315000000000
0#
#320000000000
b00000000000000000000000010110000 !
b00000000000000000000000011111010 "
1#
b00000000000000000000000010001101 %
#325000000000
0#
#330000000000
b00000000000000000000000000111000 !
b00000000000000000000000011100100 "
1#
0$
b00000000000000000000000000000000 %
#335000000000
0#
#340000000000
b00000000000000000000000001011111 !
b00000000000000000000000011000100 "
1#
#345000000000
0#
#350000000000
b00000000000000000000000010010011 !
b00000000000000000000000010001000 "
1#
#355000000000
0#
#360000000000
b00000000000000000000000000001000 !
b00000000000000000000000011011010 "
1#
1$
#365000000000
0#
#370000000000
b00000000000000000000000010100111 !
b00000000000000000000000001101011 "
1#
#375000000000
0#
#380000000000
b00000000000000000000000001110111 !
b00000000000000000000000001100000 "
1#
b00000000000000000000000000011100 %
#385000000000
0#
#390000000000
b00000000000000000000000000101001 !
b00000000000000000000000001101011 "
1#
b00000000000000000000000000000000 %
#395000000000
0#
#400000000000
b00000000000000000000000000001011 !
b00000000000000000000000000010000 "
1#
0$
b00000000000000000000000011011010 %
#405000000000
0#
#410000000000
b00000000000000000000000010010111 !
b00000000000000000000000000110010 "
1#
1$
b00000000000000000000000000000000 %
#415000000000
0#
#420000000000
b00000000000000000000000000100001 !
b00000000000000000000000011000010 "
1#
#425000000000
0#
#430000000000
b00000000000000000000000001000100 !
b00000000000000000000000010100100 "
1#
#435000000000
0#
#440000000000
b00000000000000000000000010000011 !
b00000000000000000000000011010101 "
1#
0$
#445000000000
0#
#450000000000
b00000000000000000000000000111000 !
b00000000000000000000000001011000 "
1#
1$
#455000000000
0#
#460000000000
b00000000000000000000000001110000 !
b00000000000000000000000010000000 "
1#
#465000000000
0#
#470000000000
b00000000000000000000000010000011 !
b00000000000000000000000001111010 "
1#
0$
#475000000000
0#
#480000000000
b00000000000000000000000010111100 !
b00000000000000000000000001001111 "
1#
#485000000000
0#
#490000000000
b00000000000000000000000000101110 !
b00000000000000000000000000111000 "
1#
1$
#495000000000
0#
#500000000000
b00000000000000000000000001111000 !
b00000000000000000000000011010010 "
1#
0$
b00000000000000000000000001111111 %
#505000000000
0#
#510000000000
b00000000000000000000000010000010 !
b00000000000000000000000000010101 "
1#
b00000000000000000000000000000000 %
#515000000000
0#
#520000000000
b00000000000000000000000001110001 !
b00000000000000000000000001100001 "
1#
b00000000000000000000000010000000 %
#525000000000
0#
#530000000000
b00000000000000000000000001101110 !
b00000000000000000000000011010001 "
1#
b00000000000000000000000001011111 %
#535000000000
0#
#540000000000
b00000000000000000000000000110001 !
b00000000000000000000000010011001 "
1#
b00000000000000000000000000000000 %
#545000000000
0#
#550000000000
b00000000000000000000000010111001 !
b00000000000000000000000001010010 "
1#
#555000000000
0#
#560000000000
b00000000000000000000000001111010 !
b00000000000000000000000010111110 "
1#
b00000000000000000000000001111111 %
#565000000000
0#
#570000000000
b00000000000000000000000010111010 !
b00000000000000000000000011100000 "
1#
1$
b00000000000000000000000000000000 %
#575000000000
0#
#580000000000
b00000000000000000000000000100000 !
b00000000000000000000000010001010 "
1#
0$
b00000000000000000000000011000010 %
#585000000000
0#
#590000000000
b00000000000000000000000010111101 !
b00000000000000000000000011010100 "
1#
b00000000000000000000000000000000 %
#595000000000
0#
#600000000000
b00000000000000000000000011100101 !
b00000000000000000000000010001010 "
1#
#605000000000
0#
#610000000000
b00000000000000000000000001010100 !
b00000000000000000000000011111100 "
1#
#615000000000
0#
#620000000000
b00000000000000000000000011110100 !
b00000000000000000000000000000100 "
1#
#625000000000
0#
#630000000000
b00000000000000000000000000011001 !
b00000000000000000000000010001101 "
1#
1$
#635000000000
0#
#640000000000
b00000000000000000000000001000001 !
b00000000000000000000000000000010 "
1#
0$
#645000000000
0#
#650000000000
b00000000000000000000000000010100 !
b00000000000000000000000011110100 "
1#
#655000000000
0#
#660000000000
b00000000000000000000000011111110 !
b00000000000000000000000010000010 "
1#
1$
#665000000000
0#
#670000000000
b00000000000000000000000010001110 !
b00000000000000000000000011111100 "
1#
b00000000000000000000000001000010 %
#675000000000
0#
#680000000000
b00000000000000000000000011110001 !
b00000000000000000000000001010000 "
1#
b00000000000000000000000000000000 %
#685000000000
0#
#690000000000
b00000000000000000000000001111100 !
b00000000000000000000000011100101 "
1#
b00000000000000000000000000111010 %
#695000000000
0#
#700000000000
b00000000000000000000000010010111 !
b00000000000000000000000011101011 "
1#
b00000000000000000000000000110010 %
#705000000000
0#
#710000000000
b00000000000000000000000010101110 !
b00000000000000000000000011010101 "
1#
b00000000000000000000000000000000 %
#715000000000
0#
#720000000000
b00000000000000000000000010100111 !
b00000000000000000000000000111101 "
1#
0$
b00000000000000000000000001101011 %
#725000000000
0#
#730000000000
b00000000000000000000000010010100 !
b00000000000000000000000000000100 "
1#
b00000000000000000000000011101011 %
#735000000000
0#
#740000000000
b00000000000000000000000000100101 !
b00000000000000000000000001000000 "
1#
b00000000000000000000000000000000 %
#745000000000
0#
#750000000000
b00000000000000000000000000000000 !
b00000000000000000000000010111110 "
1#
1$
b00000000000000000000000011011000 %
#755000000000
0#
#760000000000
b00000000000000000000000001001101 !
b00000000000000000000000000011110 "
1#
b00000000000000000000000011110011 %
#765000000000
0#
#770000000000
b00000000000000000000000000111000 !
b00000000000000000000000011000111 "
1#
0$
b00000000000000000000000001011000 %
#775000000000
0#
#780000000000
b00000000000000000000000010010111 !
b00000000000000000000000001101100 "
1#
1$
b00000000000000000000000011101011 %
#785000000000
0#
#790000000000
b00000000000000000000000000011001 !
b00000000000000000000000010110111 "
1#
0$
b00000000000000000000000010001101 %
#795000000000
0#
#800000000000
b00000000000000000000000010001011 !
b00000000000000000000000001011111 "
1#
1$
b00000000000000000000000010011110 %
#805000000000
0#
#810000000000
b00000000000000000000000000101100 !
b00000000000000000000000000011011 "
1#
b00000000000000000000000000111000 %
#815000000000
0#
#820000000000
b00000000000000000000000010100110 !
b00000000000000000000000010100111 "
1#
0$
b00000000000000000000000001101011 %
#825000000000
0#
#830000000000
b00000000000000000000000010010010 !
b00000000000000000000000001101110 "
1#
1$
b00000000000000000000000000000000 %
#835000000000
0#
#840000000000
b00000000000000000000000000011000 !
b00000000000000000000000010101100 "
1#
b00000000000000000000000010001101 %
#845000000000
0#
#850000000000
b00000000000000000000000000001001 !
b00000000000000000000000000000001 "
1#
0$
b00000000000000000000000011011010 %
#855000000000
0#
#860000000000
b00000000000000000000000001110011 !
b00000000000000000000000011001011 "
1#
b00000000000000000000000010000000 %
#865000000000
0#
#870000000000
b00000000000000000000000001101110 !
b00000000000000000000000011001100 "
1#
b00000000000000000000000001011111 %
#875000000000
0#
#880000000000
b00000000000000000000000000011111 !
b00000000000000000000000001001111 "
1#
b00000000000000000000000000000000 %
#885000000000
0#
#890000000000
b00000000000000000000000001001101 !
b00000000000000000000000000011100 "
1#
b00000000000000000000000000011110 %
#895000000000
0#
#900000000000
b00000000000000000000000011100111 !
b00000000000000000000000001110110 "
1#
1$
b00000000000000000000000000000000 %
#905000000000
0#
#910000000000
b00000000000000000000000010101000 !
b00000000000000000000000010000010 "
1#
#915000000000
0#
#920000000000
b00000000000000000000000010111110 !
b00000000000000000000000010101010 "
1#
#925000000000
0#
#930000000000
b00000000000000000000000011101001 !
b00000000000000000000000001010010 "
1#
#935000000000
0#
#940000000000
b00000000000000000000000011011000 !
b00000000000000000000000011001101 "
1#
0$
#945000000000
0#
#950000000000
b00000000000000000000000011011001 !
b00000000000000000000000010111011 "
1#
#955000000000
0#
#960000000000
b00000000000000000000000000011110 !
b00000000000000000000000001001111 "
1#
1$
#965000000000
0#
#970000000000
b00000000000000000000000001010101 !
b00000000000000000000000000001000 "
1#
#975000000000
0#
#980000000000
b00000000000000000000000010101001 !
b00000000000000000000000010011111 "
1#
b00000000000000000000000010000010 %
#985000000000
0#
#990000000000
b00000000000000000000000011010111 !
b00000000000000000000000001000100 "
1#
0$
b00000000000000000000000001100001 %
#995000000000
0#
#1000000000000
b00000000000000000000000001000111 !
b00000000000000000000000011101111 "
1#
1$
b00000000000000000000000010100100 %
#1005000000000
0#
#1010000000000
b00000000000000000000000011001001 !
b00000000000000000000000001110001 "
1#
b00000000000000000000000001010111 %
#1015000000000
0#
#1020000000000
b00000000000000000000000011110001 !
b00000000000000000000000000111000 "
1#
0$
b00000000000000000000000001010000 %
#1025000000000
0#
#1030000000000
b00000000000000000000000000111101 !
b00000000000000000000000010101000 "
1#
b00000000000000000000000010011111 %
#1035000000000
0#
#1040000000000
b00000000000000000000000000101110 !
b00000000000000000000000001110110 "
1#
1$
b00000000000000000000000000011011 %
#1045000000000
0#
#1050000000000
b00000000000000000000000000111010 !
b00000000000000000000000010001001 "
1#
b00000000000000000000000001011000 %
#1055000000000
0#
#1060000000000
b00000000000000000000000000011011 !
b00000000000000000000000001100101 "
1#
0$
b00000000000000000000000010101100 %
#1065000000000
0#
#1070000000000
b00000000000000000000000001100011 !
b00000000000000000000000000010001 "
1#
b00000000000000000000000000000000 %
#1075000000000
0#
#1080000000000
b00000000000000000000000010001000 !
b00000000000000000000000011110111 "
1#
1$
b00000000000000000000000001011111 %
#1085000000000
0#
#1090000000000
b00000000000000000000000011100001 !
b00000000000000000000000010101010 "
1#
b00000000000000000000000011001101 %
#1095000000000
0#
#1100000000000
b00000000000000000000000000100001 !
b00000000000000000000000010110000 "
1#
b00000000000000000000000011000010 %
#1105000000000
0#
#1110000000000
b00000000000000000000000001001010 !
b00000000000000000000000010001000 "
1#
b00000000000000000000000000000000 %
#1115000000000
0#
#1120000000000
b00000000000000000000000000110110 !
b00000000000000000000000000001101 "
1#
0$
#1125000000000
0#
#1130000000000
b00000000000000000000000010111011 !
b00000000000000000000000001011011 "
1#
b00000000000000000000000011100000 %
#1135000000000
0#
#1140000000000
b00000000000000000000000000001100 !
b00000000000000000000000000000000 "
1#
1$
b00000000000000000000000000000000 %
#1145000000000
0#
#1150000000000
b00000000000000000000000010110101 !
b00000000000000000000000000100010 "
1#
0$
#1155000000000
0#
#1160000000000
b00000000000000000000000010111001 !
b00000000000000000000000011011101 "
1#
b00000000000000000000000011100000 %
#1165000000000
0#
#1170000000000
b00000000000000000000000010011011 !
b00000000000000000000000000011110 "
1#
b00000000000000000000000000000000 %
#1175000000000
0#
#1180000000000
b00000000000000000000000011011100 !
b00000000000000000000000011000010 "
1#
1$
#1185000000000
0#
#1190000000000
b00000000000000000000000000100000 !
b00000000000000000000000010110100 "
1#
b00000000000000000000000010110000 %
#1195000000000
0#
#1200000000000
b00000000000000000000000000101010 !
b00000000000000000000000011100101 "
1#
0$
b00000000000000000000000001101011 %
#1205000000000
0#
#1210000000000
b00000000000000000000000010100101 !
b00000000000000000000000001001001 "
1#
1$
#1215000000000
0#
#1220000000000
b00000000000000000000000011010111 !
b00000000000000000000000000111011 "
1#
0$
b00000000000000000000000001100001 %
#1225000000000
0#
#1230000000000
b00000000000000000000000010001100 !
b00000000000000000000000011101000 "
1#
b00000000000000000000000011111100 %
#1235000000000
0#
#1240000000000
b00000000000000000000000011111000 !
b00000000000000000000000000111000 "
1#
1$
b00000000000000000000000000000000 %
#1245000000000
0#
#1250000000000
b00000000000000000000000001111101 !
b00000000000000000000000000101100 "
1#
b00000000000000000000000011100101 %
#1255000000000
0#
#1260000000000
b00000000000000000000000010010000 !
b00000000000000000000000000011111 "
1#
0$
b00000000000000000000000001101110 %
#1265000000000
0#
#1270000000000
b00000000000000000000000000011111 !
b00000000000000000000000011101000 "
1#
1$
b00000000000000000000000001001111 %
#1275000000000
0#
#1280000000000
b00000000000000000000000010110111 !
b00000000000000000000000000011111 "
1#
0$
b00000000000000000000000000000000 %
#1285000000000
0#
#1290000000000
b00000000000000000000000001111110 !
b00000000000000000000000000011101 "
1#
b00000000000000000000000000101100 %
#1295000000000
0#
#1300000000000
b00000000000000000000000011111110 !
b00000000000000000000000001111010 "
1#
1$
b00000000000000000000000010000010 %
#1305000000000
0#
#1310000000000
b00000000000000000000000011111011 !
b00000000000000000000000000010001 "
1#
0$
b00000000000000000000000000111000 %
#1315000000000
0#
#1320000000000
b00000000000000000000000000111100 !
b00000000000000000000000001001110 "
1#
b00000000000000000000000010011111 %
#1325000000000
0#
#1330000000000
b00000000000000000000000011111111 !
b00000000000000000000000001101011 "
1#
b00000000000000000000000001111010 %
#1335000000000
0#
#1340000000000
b00000000000000000000000010001000 !
b00000000000000000000000011000001 "
1#
1$
b00000000000000000000000011110111 %
#1345000000000
0#
#1350000000000
b00000000000000000000000010100001 !
b00000000000000000000000010111001 "
1#
b00000000000000000000000000000000 %
#1355000000000
0#
#1360000000000
b00000000000000000000000010010010 !
b00000000000000000000000001101101 "
1#
0$
b00000000000000000000000001101110 %
#1365000000000
0#
#1370000000000
b00000000000000000000000011100111 !
b00000000000000000000000011110111 "
1#
b00000000000000000000000001110110 %
#1375000000000
0#
#1380000000000
b00000000000000000000000010110000 !
b00000000000000000000000001001101 "
1#
1$
b00000000000000000000000011111010 %
#1385000000000
0#
#1390000000000
b00000000000000000000000000010100 !
b00000000000000000000000011111011 "
1#
0$
b00000000000000000000000000000000 %
#1395000000000
0#
#1400000000000
b00000000000000000000000000100100 !
b00000000000000000000000001111000 "
1#
#1405000000000
0#
#1410000000000
b00000000000000000000000010011111 !
b00000000000000000000000010101110 "
1#
#1415000000000
0#
#1420000000000
b00000000000000000000000010010101 !
b00000000000000000000000001010011 "
1#
1$
b00000000000000000000000001101100 %
#1425000000000
0#
#1430000000000
b00000000000000000000000000010111 !
b00000000000000000000000011011101 "
1#
b00000000000000000000000000000000 %
#1435000000000
0#
#1440000000000
b00000000000000000000000010110110 !
b00000000000000000000000000101101 "
1#
0$
#1445000000000
0#
#1450000000000
b00000000000000000000000000001011 !
b00000000000000000000000010111100 "
1#
b00000000000000000000000011011010 %
#1455000000000
0#
#1460000000000
b00000000000000000000000000111100 !
b00000000000000000000000000101001 "
1#
1$
b00000000000000000000000010011111 %
#1465000000000
0#
#1470000000000
b00000000000000000000000001100010 !
b00000000000000000000000000110100 "
1#
0$
b00000000000000000000000000000000 %
#1475000000000
0#
#1480000000000
b00000000000000000000000000000000 !
b00000000000000000000000000001000 "
1#
b00000000000000000000000010111110 %
#1485000000000
0#
#1490000000000
b00000000000000000000000000100010 !
b00000000000000000000000011101101 "
1#
1$
b00000000000000000000000010110100 %
#1495000000000
0#
#1500000000000
b00000000000000000000000011100011 !
b00000000000000000000000001011000 "
1#
b00000000000000000000000010101010 %
#1505000000000
0#
#1510000000000
b00000000000000000000000001000101 !
b00000000000000000000000000001110 "
1#
b00000000000000000000000011101111 %
#1515000000000
0#
#1520000000000
b00000000000000000000000011000110 !
b00000000000000000000000010111011 "
1#
b00000000000000000000000000000000 %
#1525000000000
0#
#1530000000000
b00000000000000000000000000011110 !
b00000000000000000000000010011011 "
1#
b00000000000000000000000011101000 %
#1535000000000
0#
#1540000000000
b00000000000000000000000011001100 !
b00000000000000000000000010100111 "
1#
b00000000000000000000000000000000 %
#1545000000000
0#
#1550000000000
b00000000000000000000000001101011 !
b00000000000000000000000011111100 "
1#
0$
#1555000000000
0#
#1560000000000
b00000000000000000000000011000011 !
b00000000000000000000000001100111 "
1#
#1565000000000
0#
#1570000000000
b00000000000000000000000010010110 !
b00000000000000000000000001001001 "
1#
1$
b00000000000000000000000001010011 %
#1575000000000
0#
#1580000000000
b00000000000000000000000010101010 !
b00000000000000000000000000110010 "
1#
0$
b00000000000000000000000010011111 %
#1585000000000
0#
#1590000000000
b00000000000000000000000001100110 !
b00000000000000000000000001111001 "
1#
1$
b00000000000000000000000001100101 %
#1595000000000
0#
#1600000000000
b00000000000000000000000000111111 !
b00000000000000000000000010111000 "
1#
b00000000000000000000000000101001 %
#1605000000000
0#
#1610000000000
b00000000000000000000000001000101 !
b00000000000000000000000000001111 "
1#
0$
b00000000000000000000000000001110 %
#1615000000000
0#
#1620000000000
b00000000000000000000000001001100 !
b00000000000000000000000001111100 "
1#
b00000000000000000000000000011110 %
#1625000000000
0#
#1630000000000
b00000000000000000000000001100110 !
b00000000000000000000000011000110 "
1#
1$
b00000000000000000000000001111001 %
#1635000000000
0#
#1640000000000
b00000000000000000000000011000000 !
b00000000000000000000000010101001 "
1#
0$
b00000000000000000000000000000000 %
#1645000000000
0#
#1650000000000
b00000000000000000000000000101110 !
b00000000000000000000000000111001 "
1#
b00000000000000000000000001110110 %
#1655000000000
0#
#1660000000000
b00000000000000000000000011110010 !
b00000000000000000000000010111111 "
1#
1$
b00000000000000000000000001010000 %
#1665000000000
0#
#1670000000000
b00000000000000000000000001011111 !
b00000000000000000000000001000111 "
1#
b00000000000000000000000000000000 %
#1675000000000
0#
#1680000000000
b00000000000000000000000011100100 !
b00000000000000000000000010011100 "
1#
b00000000000000000000000001110110 %
#1685000000000
0#
#1690000000000
b00000000000000000000000001101000 !
b00000000000000000000000000111110 "
1#
0$
b00000000000000000000000000000000 %
#1695000000000
0#
#1700000000000
b00000000000000000000000011100100 !
b00000000000000000000000001110010 "
1#
1$
b00000000000000000000000010011100 %
#1705000000000
0#
#1710000000000
b00000000000000000000000001000001 !
b00000000000000000000000001000011 "
1#
0$
b00000000000000000000000000000000 %
#1715000000000
0#
#1720000000000
b00000000000000000000000011010111 !
b00000000000000000000000011000011 "
1#
1$
b00000000000000000000000001100001 %
#1725000000000
0#
#1730000000000
b00000000000000000000000010010010 !
b00000000000000000000000010100110 "
1#
0$
b00000000000000000000000001101110 %
#1735000000000
0#
#1740000000000
b00000000000000000000000010010001 !
b00000000000000000000000000111011 "
1#
#1745000000000
0#
#1750000000000
b00000000000000000000000011001111 !
b00000000000000000000000000101010 "
1#
b00000000000000000000000010100111 %
#1755000000000
0#
#1760000000000
b00000000000000000000000011001001 !
b00000000000000000000000001100000 "
1#
1$
b00000000000000000000000001110001 %
#1765000000000
0#
#1770000000000
b00000000000000000000000000100110 !
b00000000000000000000000000011000 "
1#
0$
b00000000000000000000000000000000 %
#1775000000000
0#
#1780000000000
b00000000000000000000000000010000 !
b00000000000000000000000001000101 "
1#
1$
#1785000000000
0#
#1790000000000
b00000000000000000000000000001010 !
b00000000000000000000000001000010 "
1#
b00000000000000000000000011011010 %
#1795000000000
0#
#1800000000000
b00000000000000000000000001010101 !
b00000000000000000000000000111000 "
1#
0$
b00000000000000000000000000001000 %
#1805000000000
0#
#1810000000000
b00000000000000000000000011001111 !
b00000000000000000000000000011111 "
1#
1$
b00000000000000000000000010100111 %
#1815000000000
0#
#1820000000000
b00000000000000000000000001100110 !
b00000000000000000000000000000101 "
1#
b00000000000000000000000011000110 %
#1825000000000
0#
#1830000000000
b00000000000000000000000011100000 !
b00000000000000000000000010001010 "
1#
b00000000000000000000000001011000 %
#1835000000000
0#
#1840000000000
b00000000000000000000000011011100 !
b00000000000000000000000011011111 "
1#
b00000000000000000000000011000010 %
#1845000000000
0#
#1850000000000
b00000000000000000000000001110011 !
b00000000000000000000000010100110 "
1#
b00000000000000000000000010000000 %
#1855000000000
0#
#1860000000000
b00000000000000000000000001111011 !
b00000000000000000000000011110011 "
1#
b00000000000000000000000001111111 %
#1865000000000
0#
#1870000000000
b00000000000000000000000011110110 !
b00000000000000000000000010100011 "
1#
0$
b00000000000000000000000000000000 %
#1875000000000
0#
#1880000000000
b00000000000000000000000001100001 !
b00000000000000000000000010110101 "
1#
#1885000000000
0#
#1890000000000
b00000000000000000000000001111001 !
b00000000000000000000000000100111 "
1#
b00000000000000000000000011110011 %
#1895000000000
0#
#1900000000000
b00000000000000000000000001101001 !
b00000000000000000000000001111110 "
1#
1$
b00000000000000000000000000000000 %
#1905000000000
0#
#1910000000000
b00000000000000000000000010110000 !
b00000000000000000000000000100100 "
1#
0$
b00000000000000000000000001001101 %
#1915000000000
0#
#1920000000000
b00000000000000000000000011101000 !
b00000000000000000000000011100101 "
1#
1$
b00000000000000000000000001010010 %
#1925000000000
0#
#1930000000000
b00000000000000000000000011001110 !
b00000000000000000000000000110011 "
1#
b00000000000000000000000000011111 %
#1935000000000
0#
#1940000000000
b00000000000000000000000000101011 !
b00000000000000000000000001000101 "
1#
0$
b00000000000000000000000001101011 %
#1945000000000
0#
#1950000000000
b00000000000000000000000010001000 !
b00000000000000000000000011011000 "
1#
1$
b00000000000000000000000011000001 %
#1955000000000
0#
#1960000000000
b00000000000000000000000000110011 !
b00000000000000000000000010001110 "
1#
0$
b00000000000000000000000000000000 %
#1965000000000
0#
#1970000000000
b00000000000000000000000001101100 !
b00000000000000000000000001110111 "
1#
b00000000000000000000000001011111 %
#1975000000000
0#
#1980000000000
b00000000000000000000000011001110 !
b00000000000000000000000000100001 "
1#
b00000000000000000000000000110011 %
#1985000000000
0#
#1990000000000
b00000000000000000000000000001011 !
b00000000000000000000000001101010 "
1#
1$
b00000000000000000000000001000010 %
#1995000000000
0#
#2000000000000
b00000000000000000000000000110100 !
b00000000000000000000000001110011 "
1#
b00000000000000000000000000000000 %
#2005000000000
0#
#2010000000000
b00000000000000000000000011010010 !
b00000000000000000000000011010010 "
1#
#2015000000000
0#
#2020000000000
b00000000000000000000000001000110 !
b00000000000000000000000001000101 "
1#
0$
b00000000000000000000000000001110 %
#2025000000000
0#
#2030000000000
b00000000000000000000000010111101 !
b00000000000000000000000000101010 "
1#
1$
b00000000000000000000000010101010 %
#2035000000000
0#
#2040000000000
b00000000000000000000000000111101 !
b00000000000000000000000001110001 "
1#
0$
b00000000000000000000000010111000 %
#2045000000000
0#
#2050000000000
b00000000000000000000000011010100 !
b00000000000000000000000000011011 "
1#
b00000000000000000000000011000011 %
#2055000000000
0#
#2060000000000
b00000000000000000000000001011000 !
b00000000000000000000000011000010 "
1#
b00000000000000000000000001111111 %
#2065000000000
0#
#2070000000000
b00000000000000000000000011100000 !
b00000000000000000000000000001001 "
1#
1$
b00000000000000000000000010001010 %
#2075000000000
0#
#2080000000000
b00000000000000000000000000111111 !
b00000000000000000000000001001011 "
1#
0$
b00000000000000000000000010111000 %
#2085000000000
0#
#2090000000000
b00000000000000000000000000011001 !
b00000000000000000000000000011001 "
1#
b00000000000000000000000010101100 %
#2095000000000
0#
#2100000000000
b00000000000000000000000001101011 !
b00000000000000000000000010010001 "
1#
1$
b00000000000000000000000001111110 %
#2105000000000
0#
#2110000000000
b00000000000000000000000011110001 !
b00000000000000000000000000001100 "
1#
b00000000000000000000000010111111 %
#2115000000000
0#
#2120000000000
b00000000000000000000000001110110 !
b00000000000000000000000010101000 "
1#
b00000000000000000000000001100000 %
#2125000000000
0#
#2130000000000
b00000000000000000000000001011100 !
b00000000000000000000000001111110 "
1#
b00000000000000000000000001000111 %
#2135000000000
0#
#2140000000000
b00000000000000000000000010100010 !
b00000000000000000000000010111101 "
1#
b00000000000000000000000010111001 %
#2145000000000
0#
#2150000000000
b00000000000000000000000001000111 !
b00000000000000000000000010100001 "
1#
b00000000000000000000000000001110 %
#2155000000000
0#
#2160000000000
b00000000000000000000000011111100 !
b00000000000000000000000011111111 "
1#
b00000000000000000000000001111010 %
#2165000000000
0#
#2170000000000
b00000000000000000000000000011001 !
b00000000000000000000000001001100 "
1#
0$
b00000000000000000000000010101100 %
#2175000000000
0#
#2180000000000
b00000000000000000000000000000010 !
b00000000000000000000000011111011 "
1#
b00000000000000000000000010111110 %
#2185000000000
0#
#2190000000000
b00000000000000000000000000100111 !
b00000000000000000000000010000111 "
1#
b00000000000000000000000000000000 %
#2195000000000
0#
#2200000000000
b00000000000000000000000001001110 !
b00000000000000000000000010011100 "
1#
b00000000000000000000000000011110 %
#2205000000000
0#
#2210000000000
b00000000000000000000000011011001 !
b00000000000000000000000000110001 "
1#
b00000000000000000000000000000000 %
#2215000000000
0#
#2220000000000
b00000000000000000000000000010101 !
b00000000000000000000000001101001 "
1#
b00000000000000000000000011011101 %
#2225000000000
0#
#2230000000000
b00000000000000000000000011110110 !
b00000000000000000000000011011100 "
1#
1$
b00000000000000000000000000000000 %
#2235000000000
0#
#2240000000000
b00000000000000000000000011111011 !
b00000000000000000000000001110001 "
1#
0$
b00000000000000000000000000111000 %
#2245000000000
0#
#2250000000000
b00000000000000000000000010111010 !
b00000000000000000000000000010111 "
1#
b00000000000000000000000011100000 %
#2255000000000
0#
#2260000000000
b00000000000000000000000001001111 !
b00000000000000000000000011010111 "
1#
1$
b00000000000000000000000000011110 %
#2265000000000
0#
#2270000000000
b00000000000000000000000000100111 !
b00000000000000000000000010000111 "
1#
b00000000000000000000000000000000 %
#2275000000000
0#
#2280000000000
b00000000000000000000000000001000 !
b00000000000000000000000011111001 "
1#
0$
b00000000000000000000000001101010 %
#2285000000000
0#
#2290000000000
b00000000000000000000000011001010 !
b00000000000000000000000010100111 "
1#
b00000000000000000000000001100000 %
#2295000000000
0#
#2300000000000
b00000000000000000000000000011001 !
b00000000000000000000000001010101 "
1#
1$
b00000000000000000000000010101100 %
#2305000000000
0#
#2310000000000
b00000000000000000000000010011111 !
b00000000000000000000000000101001 "
1#
b00000000000000000000000000000000 %
#2315000000000
0#
#2320000000000
b00000000000000000000000011111101 !
b00000000000000000000000011111001 "
1#
0$
b00000000000000000000000011111111 %
#2325000000000
0#
#2330000000000
b00000000000000000000000001000000 !
b00000000000000000000000000001000 "
1#
b00000000000000000000000000000000 %
#2335000000000
0#
