rtl/ALU.vhdl
library ieee;
use ieee.std_logic_1164.all;
use ieee.numeric_std.all;

entity ALU is
    port(
        SrcA : in std_logic_vector(31 downto 0);
        SrcB : in std_logic_vector(31 downto 0);
        ALUControl : in std_logic_vector(2 downto 0);
        Zero : out std_logic;
        ALUResult : buffer std_logic_vector(31 downto 0)
    );
end ALU;

architecture rtl of ALU is

    signal alu_res : std_logic_vector(31 downto 0);

    begin
        process(SrcA, SrcB, ALUControl)begin
            case ALUControl is
                --add
                when "000" => ALUResult <= std_logic_vector(unsigned(SrcA) + unsigned(SrcB));
                --sub
                when "001" => ALUResult <= std_logic_vector(unsigned(SrcA) - unsigned(SrcB));
                --and
                when "010" => ALUResult <= SrcA and SrcB;
                --or
                when "011" => ALUResult <=  SrcA or SrcB;
                --srl
                when "100" => ALUResult <= std_logic_vector(unsigned(SrcA) srl to_integer(unsigned(SrcB)));
                --xor
                when "110" => ALUResult <= SrcA xor SrcB;
                --sll
                when "111" => ALUResult <= std_logic_vector(unsigned(SrcA) sll to_integer(unsigned(SrcB)));
                --slt
                when "101" =>
                    if(SrcA < SrcB)then
                        ALUResult <= x"00000001";
                    else
                    ALUResult <= x"00000000";
                    end if;
                when others => ALUResult <= (others => 'U');
                end case;
            end process;

            Zero <= '1' when ALUResult = x"00000000" else '0';

            --ALUResult <= alu_res;
    end rtl;

ALU/anyname.vcd
$date
  Thu Dec 16 23:11:07 2021
$end
$version
  GHDL v0
$end
$timescale
  1 fs
$end
$scope module standard $end
$upscope $end
$scope module std_logic_1164 $end
$upscope $end
$scope module numeric_std $end
$upscope $end
$scope module alu $end
$var reg 32 ! srca[31:0] $end
$var reg 32 " srcb[31:0] $end
$var reg 3 # alucontrol[2:0] $end
$var reg 1 $ zero $end
$var reg 32 % aluresult[31:0] $end
$var reg 32 & alu_res[31:0] $end
$upscope $end
$enddefinitions $end
#0
b00000000000000001001001010001110 !
b00000000000000000101111000110101 "
b110 #
0$
b00000000000000001100110010111011 %
b00000000000000001100110010111011 &
#5000000
b00000000000000000111100101111111 !
b00000000000000000000100000010011 "
b101 #
1$
b00000000000000000000000000000000 %
b00000000000000000000000000000000 &
#10000000
b00000000000000001010001110000010 !
b00000000000000000001001101100111 "
b111 #
#15000000
b00000000000000000110001110010010 !
b00000000000000001100000100101011 "
b101 #
0$
b00000000000000000000000000000001 %
b00000000000000000000000000000001 &
#20000000
b00000000000000000110001100111101 !
b00000000000000000111011011011100 "
b000 #
b00000000000000001101101000011001 %
b00000000000000001101101000011001 &
#25000000
b00000000000000001000000001101000 !
b00000000000000001000001000101110 "
b00000000000000010000001010010110 %
b00000000000000010000001010010110 &
#30000000
b00000000000000001010011111110011 !
b00000000000000000011000000010111 "
b001 #
b00000000000000000111011111011100 %
b00000000000000000111011111011100 &
#35000000
b00000000000000001001011001000011 !
b00000000000000001011111110011011 "
b11111111111111111101011010101000 %
b11111111111111111101011010101000 &
#40000000
b00000000000000001010011000101101 !
b00000000000000000011001111011000 "
b110 #
b00000000000000001001010111110101 %
b00000000000000001001010111110101 &
#45000000
b00000000000000001000101000100100 !
b00000000000000000010100111110110 "
b000 #
b00000000000000001011010000011010 %
b00000000000000001011010000011010 &
#50000000
b00000000000000000100010110101111 !
b00000000000000000110111000111011 "
b001 #
b11111111111111111101011101110100 %
b11111111111111111101011101110100 &
#55000000
b00000000000000000001110010001011 !
b00000000000000000011000110111011 "
b110 #
b00000000000000000010110100110000 %
b00000000000000000010110100110000 &
#60000000
b00000000000000000010100100010100 !
b00000000000000000101010101011011 "
b011 #
b00000000000000000111110101011111 %
b00000000000000000111110101011111 &
#65000000
b00000000000000000000011101110110 !
b00000000000000001010010011001100 "
b100 #
1$
b00000000000000000000000000000000 %
b00000000000000000000000000000000 &
#70000000
b00000000000000000000011100010011 !
b00000000000000001011110111111111 "
b110 #
0$
b00000000000000001011101011101100 %
b00000000000000001011101011101100 &
